hearthstone_card_generator/__init__.py
hearthstone_card_generator/card_generator.py
hearthstone_card_generator/card_generator_test.py
hearthstone_card_generator/card_information_database.py
hearthstone_card_generator/hearthstone_card.py
hearthstone_card_generator-1.5.dist-info/METADATA
hearthstone_card_generator-1.5.dist-info/WHEEL
hearthstone_card_generator-1.5.dist-info/top_level.txt
hearthstone_card_generator-1.5.dist-info/RECORD
