Metadata-Version: 2.1
Name: hearthstone-card-generator
Version: 1.5
Summary: Generates completely random hearthstone cards (random mana cost, attack, health, name, and a description generated using markov chains from existing descriptions)
Home-page: https://github.com/maymike321/hearthstone_card_generator
Author: Michael May
Author-email: yamekim@comcast.net
License: MIT
Platform: UNKNOWN
Requires-Dist: pyykov
